README.rst
setup.py
buildr/__init__.py
buildr/__main__.py
buildr/abc.py
buildr/buildr.py
buildr/exc.py
buildr/manifest.py
buildr.egg-info/PKG-INFO
buildr.egg-info/SOURCES.txt
buildr.egg-info/dependency_links.txt
buildr.egg-info/entry_points.txt
buildr.egg-info/not-zip-safe
buildr.egg-info/requires.txt
buildr.egg-info/top_level.txt