Metadata-Version: 1.1
Name: buildr
Version: 0.1.2
Summary: Simple build manifest runner, mounting the build container via docker.
Home-page: https://github.com/mrasband/builder_ci
Author: Matt Rasband
Author-email: matt.rasband@gmail.com
License: Apache-2.0
Download-URL: https://github.com/mrasband/builder_ci/archive/v0.1.2.tar.gz
Keywords: ci,build
Platform: UNKNOWN
Classifier: Programming Language :: Python :: 3.5
Classifier: License :: OSI Approved :: Apache Software License
Classifier: Intended Audience :: Developers
Classifier: Development Status :: 4 - Beta
Classifier: Topic :: Software Development
